{
 "custom_fields": [
  {
   "_assign": null,
   "_comments": null,
   "_liked_by": null,
   "_user_tags": null,
   "allow_on_submit": 0,
   "bold": 0,
   "collapsible": 0,
   "collapsible_depends_on": null,
   "columns": 0,
   "creation": "2019-02-04 13:56:50.165984",
   "default": null,
   "depends_on": null,
   "description": null,
   "docstatus": 0,
   "dt": "Sales Order",
   "fetch_from": null,
   "fieldname": "submitted_by",
   "fieldtype": "Link",
   "hidden": 0,
   "idx": 100,
   "ignore_user_permissions": 0,
   "ignore_xss_filter": 0,
   "in_filter": 0,
   "in_filter_dash": 0,
   "in_global_search": 0,
   "in_list_view": 0,
   "in_standard_filter": 0,
   "insert_after": "project",
   "label": "Submitted By",
   "modified": "2019-02-04 13:56:50.165984",
   "modified_by": "Administrator",
   "name": "Sales Order-submitted_by",
   "no_copy": 0,
   "options": "User",
   "owner": "Administrator",
   "parent": null,
   "parentfield": null,
   "parenttype": null,
   "permlevel": 2,
   "precision": "",
   "print_hide": 0,
   "print_hide_if_no_value": 0,
   "print_width": null,
   "read_only": 1,
   "report_hide": 0,
   "reqd": 0,
   "search_index": 0,
   "translatable": 0,
   "unique": 0,
   "width": null
  },
  {
   "_assign": null,
   "_comments": null,
   "_liked_by": null,
   "_user_tags": null,
   "allow_on_submit": 0,
   "bold": 0,
   "collapsible": 0,
   "collapsible_depends_on": null,
   "columns": 0,
   "creation": "2019-01-23 08:56:02.336418",
   "default": null,
   "depends_on": null,
   "description": null,
   "docstatus": 0,
   "dt": "Sales Order",
   "fetch_from": "company_address.gstin",
   "fieldname": "company_gstin",
   "fieldtype": "Data",
   "hidden": 0,
   "idx": 26,
   "ignore_user_permissions": 0,
   "ignore_xss_filter": 0,
   "in_filter": 0,
   "in_filter_dash": 0,
   "in_global_search": 0,
   "in_list_view": 0,
   "in_standard_filter": 0,
   "insert_after": "company_address",
   "label": "Company GSTIN",
   "modified": "2019-01-23 08:56:02.336418",
   "modified_by": "Administrator",
   "name": "Sales Order-company_gstin",
   "no_copy": 0,
   "options": null,
   "owner": "Administrator",
   "parent": null,
   "parentfield": null,
   "parenttype": null,
   "permlevel": 0,
   "precision": "",
   "print_hide": 1,
   "print_hide_if_no_value": 0,
   "print_width": null,
   "read_only": 0,
   "report_hide": 0,
   "reqd": 0,
   "search_index": 0,
   "translatable": 1,
   "unique": 0,
   "width": null
  },
  {
   "_assign": null,
   "_comments": null,
   "_liked_by": null,
   "_user_tags": null,
   "allow_on_submit": 0,
   "bold": 0,
   "collapsible": 0,
   "collapsible_depends_on": null,
   "columns": 0,
   "creation": "2019-01-23 08:55:55.219167",
   "default": null,
   "depends_on": null,
   "description": null,
   "docstatus": 0,
   "dt": "Sales Order",
   "fetch_from": null,
   "fieldname": "place_of_supply",
   "fieldtype": "Data",
   "hidden": 0,
   "idx": 30,
   "ignore_user_permissions": 0,
   "ignore_xss_filter": 0,
   "in_filter": 0,
   "in_filter_dash": 0,
   "in_global_search": 0,
   "in_list_view": 0,
   "in_standard_filter": 0,
   "insert_after": "customer_gstin",
   "label": "Place of Supply",
   "modified": "2019-01-23 08:55:55.219167",
   "modified_by": "Administrator",
   "name": "Sales Order-place_of_supply",
   "no_copy": 0,
   "options": null,
   "owner": "Administrator",
   "parent": null,
   "parentfield": null,
   "parenttype": null,
   "permlevel": 0,
   "precision": "",
   "print_hide": 1,
   "print_hide_if_no_value": 0,
   "print_width": null,
   "read_only": 0,
   "report_hide": 0,
   "reqd": 0,
   "search_index": 0,
   "translatable": 1,
   "unique": 0,
   "width": null
  },
  {
   "_assign": null,
   "_comments": null,
   "_liked_by": null,
   "_user_tags": null,
   "allow_on_submit": 0,
   "bold": 0,
   "collapsible": 0,
   "collapsible_depends_on": null,
   "columns": 0,
   "creation": "2019-01-23 08:55:48.972770",
   "default": null,
   "depends_on": null,
   "description": null,
   "docstatus": 0,
   "dt": "Sales Order",
   "fetch_from": "shipping_address_name.gstin",
   "fieldname": "customer_gstin",
   "fieldtype": "Data",
   "hidden": 0,
   "idx": 29,
   "ignore_user_permissions": 0,
   "ignore_xss_filter": 0,
   "in_filter": 0,
   "in_filter_dash": 0,
   "in_global_search": 0,
   "in_list_view": 0,
   "in_standard_filter": 0,
   "insert_after": "shipping_address_name",
   "label": "Customer GSTIN",
   "modified": "2019-01-23 08:55:48.972770",
   "modified_by": "Administrator",
   "name": "Sales Order-customer_gstin",
   "no_copy": 0,
   "options": null,
   "owner": "Administrator",
   "parent": null,
   "parentfield": null,
   "parenttype": null,
   "permlevel": 0,
   "precision": "",
   "print_hide": 1,
   "print_hide_if_no_value": 0,
   "print_width": null,
   "read_only": 0,
   "report_hide": 0,
   "reqd": 0,
   "search_index": 0,
   "translatable": 1,
   "unique": 0,
   "width": null
  },
  {
   "_assign": null,
   "_comments": null,
   "_liked_by": null,
   "_user_tags": null,
   "allow_on_submit": 0,
   "bold": 0,
   "collapsible": 0,
   "collapsible_depends_on": null,
   "columns": 0,
   "creation": "2019-01-23 08:55:40.773577",
   "default": null,
   "depends_on": null,
   "description": null,
   "docstatus": 0,
   "dt": "Sales Order",
   "fetch_from": "customer_address.gstin",
   "fieldname": "billing_address_gstin",
   "fieldtype": "Data",
   "hidden": 0,
   "idx": 18,
   "ignore_user_permissions": 0,
   "ignore_xss_filter": 0,
   "in_filter": 0,
   "in_filter_dash": 0,
   "in_global_search": 0,
   "in_list_view": 0,
   "in_standard_filter": 0,
   "insert_after": "customer_address",
   "label": "Billing Address GSTIN",
   "modified": "2019-01-23 08:55:40.773577",
   "modified_by": "Administrator",
   "name": "Sales Order-billing_address_gstin",
   "no_copy": 0,
   "options": null,
   "owner": "Administrator",
   "parent": null,
   "parentfield": null,
   "parenttype": null,
   "permlevel": 0,
   "precision": "",
   "print_hide": 1,
   "print_hide_if_no_value": 0,
   "print_width": null,
   "read_only": 0,
   "report_hide": 0,
   "reqd": 0,
   "search_index": 0,
   "translatable": 1,
   "unique": 0,
   "width": null
  },
  {
   "_assign": null,
   "_comments": null,
   "_liked_by": null,
   "_user_tags": null,
   "allow_on_submit": 1,
   "bold": 0,
   "collapsible": 0,
   "collapsible_depends_on": null,
   "columns": 0,
   "creation": "2013-07-06 15:25:16",
   "default": "Awaited",
   "depends_on": "eval:doc.order_type == 'Trial Order'",
   "description": null,
   "docstatus": 0,
   "dt": "Sales Order",
   "fetch_from": null,
   "fieldname": "trial_status",
   "fieldtype": "Select",
   "hidden": 0,
   "idx": 125,
   "ignore_user_permissions": 0,
   "ignore_xss_filter": 0,
   "in_filter": 0,
   "in_filter_dash": 0,
   "in_global_search": 0,
   "in_list_view": 0,
   "in_standard_filter": 0,
   "insert_after": "sales_team",
   "label": "Trial Status",
   "modified": "2016-06-29 11:06:53.573552",
   "modified_by": "aditya@rigpl.com",
   "name": "Sales Order-trial_status",
   "no_copy": 0,
   "options": "\nApproved\nRejected\nAwaited",
   "owner": "aditya@rigpl.com",
   "parent": null,
   "parentfield": null,
   "parenttype": null,
   "permlevel": 3,
   "precision": null,
   "print_hide": 0,
   "print_hide_if_no_value": 0,
   "print_width": null,
   "read_only": 0,
   "report_hide": 0,
   "reqd": 0,
   "search_index": 0,
   "translatable": 1,
   "unique": 0,
   "width": null
  },
  {
   "_assign": null,
   "_comments": null,
   "_liked_by": null,
   "_user_tags": null,
   "allow_on_submit": 0,
   "bold": 0,
   "collapsible": 0,
   "collapsible_depends_on": null,
   "columns": 0,
   "creation": "2015-04-25 15:28:08.949692",
   "default": null,
   "depends_on": null,
   "description": null,
   "docstatus": 0,
   "dt": "Sales Order",
   "fetch_from": null,
   "fieldname": "track_trial",
   "fieldtype": "Check",
   "hidden": 0,
   "idx": 37,
   "ignore_user_permissions": 0,
   "ignore_xss_filter": 0,
   "in_filter": 0,
   "in_filter_dash": 0,
   "in_global_search": 0,
   "in_list_view": 0,
   "in_standard_filter": 0,
   "insert_after": "currency",
   "label": "Track Trial",
   "modified": "2016-06-29 11:06:45.802439",
   "modified_by": "aditya@rigpl.com",
   "name": "Sales Order-track_trial",
   "no_copy": 1,
   "options": null,
   "owner": "aditya@rigpl.com",
   "parent": null,
   "parentfield": null,
   "parenttype": null,
   "permlevel": 3,
   "precision": "",
   "print_hide": 0,
   "print_hide_if_no_value": 0,
   "print_width": null,
   "read_only": 0,
   "report_hide": 0,
   "reqd": 0,
   "search_index": 0,
   "translatable": 1,
   "unique": 0,
   "width": null
  },
  {
   "_assign": null,
   "_comments": null,
   "_liked_by": null,
   "_user_tags": null,
   "allow_on_submit": 0,
   "bold": 0,
   "collapsible": 0,
   "collapsible_depends_on": null,
   "columns": 0,
   "creation": "2013-01-08 08:13:12",
   "default": null,
   "depends_on": null,
   "description": null,
   "docstatus": 0,
   "dt": "Sales Order",
   "fetch_from": null,
   "fieldname": "shipping_address_title",
   "fieldtype": "Data",
   "hidden": 0,
   "idx": 31,
   "ignore_user_permissions": 0,
   "ignore_xss_filter": 0,
   "in_filter": 0,
   "in_filter_dash": 0,
   "in_global_search": 0,
   "in_list_view": 0,
   "in_standard_filter": 0,
   "insert_after": "place_of_supply",
   "label": "Shipping Address Title",
   "modified": "2016-06-29 11:06:44.470188",
   "modified_by": "aditya@rigpl.com",
   "name": "Sales Order-shipping_address_title",
   "no_copy": 0,
   "options": null,
   "owner": "aditya@rigpl.com",
   "parent": null,
   "parentfield": null,
   "parenttype": null,
   "permlevel": 1,
   "precision": null,
   "print_hide": 0,
   "print_hide_if_no_value": 0,
   "print_width": null,
   "read_only": 1,
   "report_hide": 0,
   "reqd": 0,
   "search_index": 0,
   "translatable": 1,
   "unique": 0,
   "width": null
  }
 ],
 "custom_perms": [],
 "doctype": "Sales Order",
 "property_setters": [],
 "sync_on_migrate": 1
}